{
  "title": "Dojo Bolt Gen v05",
  "handle": "dojo-bolt-gen-v05",
  "description": " x LOCAL SYNC\nx GIT SYNC\n x POLAR SYNC \n x WEBSITE SYNC",
  "vendor": "The Well Tarot",
  "product_type": "Blender Add-on",
  "tags": [
    "blender",
    "addon",
    "3d",
    "asset"
  ],
  "status": "active",
  "variants": [
    {
      "price": "6.66",
      "sku": "NO3D-TOOLS-DOJO-BOLT-GEN-V05",
      "inventory_policy": "continue",
      "inventory_management": "shopify"
    }
  ],
  "metafields": [
    {
      "namespace": "no3d_tools",
      "key": "asset_type",
      "value": "GEOMETRY",
      "type": "single_line_text_field"
    },
    {
      "namespace": "no3d_tools",
      "key": "blender_version",
      "value": "5.0.0+",
      "type": "single_line_text_field"
    },
    {
      "namespace": "no3d_tools",
      "key": "export_date",
      "value": "2025-11-15",
      "type": "date"
    },
    {
      "namespace": "no3d_tools",
      "key": "source_file",
      "value": "NO3D TOOLS workbench_23oct2025.blend",
      "type": "single_line_text_field"
    },
    {
      "namespace": "no3d_tools",
      "key": "blend_file",
      "value": "Dojo Bolt Gen v05.blend",
      "type": "single_line_text_field"
    },
    {
      "namespace": "no3d_tools",
      "key": "thumbnail",
      "value": "icon_Dojo Bolt Gen v05.png",
      "type": "single_line_text_field"
    }
  ],
  "polar": {
    "product_id": "2fbe03f5-f6bc-4d53-a309-1b9aa7fa010c",
    "benefit_id": "24ccf893-6439-4e5c-8a99-6461ff8e4d75",
    "file_id": "45153005-40bc-4414-a7b8-e9ad25f49ff3",
    "last_synced": "2025-11-16T13:39:53.645Z",
    "price_id": "514cf2d7-e997-4559-ac67-647c4e35d9b5"
  },
  "changelog": [
    {
      "version": ".00",
      "date": "2025-11-12",
      "changes": [
        "First pass"
      ]
    },
    {
      "version": ".10",
      "date": "2025-11-15",
      "changes": [
        "updated gizmo behavior"
      ]
    }
  ]
}